aas_timeseries/__init__.py
aas_timeseries/backports.py
aas_timeseries/colors.py
aas_timeseries/conftest.py
aas_timeseries/data.py
aas_timeseries/layers.py
aas_timeseries/matplotlib.py
aas_timeseries/traits.py
aas_timeseries/views.py
aas_timeseries/visualization.py
aas_timeseries/screenshot/__init__.py
aas_timeseries/screenshot/data_server.py
aas_timeseries/screenshot/qt_web_widget.py
aas_timeseries/screenshot/screenshot.py
aas_timeseries/screenshot/setup_package.py
aas_timeseries/screenshot/template.html
aas_timeseries/screenshot/tests/__init__.py
aas_timeseries/screenshot/tests/test_screenshot.py
aas_timeseries/tests/__init__.py
aas_timeseries/tests/helpers.py
aas_timeseries/tests/test_layers.py
aas_timeseries/tests/test_matplotlib.py
aas_timeseries/tests/test_visualization.py
aas_timeseries/tests/data/phase.csv
aas_timeseries/tests/data/basic/data_daea58ba-4c73-4942-8d87-78e7d340bbcd.csv
aas_timeseries/tests/data/basic/figure.json
aas_timeseries/tests/data/basic/figure.png
aas_timeseries/tests/data/basic/figure_mpl.png
aas_timeseries/tests/data/mixed_time_axes/data_daea58ba-4c73-4942-8d87-78e7d340bbcd.csv
aas_timeseries/tests/data/mixed_time_axes/figure.json
aas_timeseries/tests/data/mixed_time_axes/figure.png
aas_timeseries/tests/data/mixed_time_axes/figure_mpl.png
aas_timeseries/tests/data/mixed_time_axes/figure_mpl_view1.png
aas_timeseries/tests/data/mixed_time_axes/figure_mpl_view2.png
aas_timeseries/tests/data/mixed_time_axes/figure_mpl_view3.png
aas_timeseries/tests/data/mixed_time_axes/figure_mpl_view4.png
aas_timeseries/tests/data/mixed_time_axes/figure_mpl_view5.png
aas_timeseries/tests/data/mixed_time_axes/figure_view1.png
aas_timeseries/tests/data/mixed_time_axes/figure_view2.png
aas_timeseries/tests/data/mixed_time_axes/figure_view3.png
aas_timeseries/tests/data/mixed_time_axes/figure_view4.png
aas_timeseries/tests/data/mixed_time_axes/figure_view5.png
aas_timeseries/tests/data/mixed_time_axes_custom_format/figure.png
aas_timeseries-0.1b4.dist-info/LICENSE.rst
aas_timeseries-0.1b4.dist-info/METADATA
aas_timeseries-0.1b4.dist-info/WHEEL
aas_timeseries-0.1b4.dist-info/top_level.txt
aas_timeseries-0.1b4.dist-info/RECORD
