Metadata-Version: 2.1
Name: aas-timeseries
Version: 0.1b4
Summary: Experimental package to make interactive visualizations for time series, for AAS Publications
Home-page: http://aas-timeseries.readthedocs.io
Author: Thomas Robitaille
Author-email: thomas.robitaille@gmail.com
License: BSD 3-Clause
Platform: UNKNOWN
Requires-Python: >=3.6
Requires-Dist: traitlets
Requires-Dist: palettable
Requires-Dist: astropy
Requires-Dist: jupyter-aas-timeseries
Requires-Dist: matplotlib
Provides-Extra: docs
Requires-Dist: sphinx-astropy ; extra == 'docs'
Requires-Dist: nbsphinx ; extra == 'docs'
Requires-Dist: sphinx-rtd-theme ; extra == 'docs'
Provides-Extra: test
Requires-Dist: pytest-astropy ; extra == 'test'
Requires-Dist: pytest-cov ; extra == 'test'
Requires-Dist: qtpy ; extra == 'test'
Requires-Dist: PyQt5 (<5.14,>=5.12) ; extra == 'test'
Requires-Dist: PyQtWebEngine (<5.14) ; extra == 'test'
Requires-Dist: tornado ; extra == 'test'
Requires-Dist: faker ; extra == 'test'
